guardian/__init__.py
guardian/core.py
guardian/utils.py
no1_2exit-1.0.dist-info/METADATA
no1_2exit-1.0.dist-info/WHEEL
no1_2exit-1.0.dist-info/top_level.txt
no1_2exit-1.0.dist-info/RECORD
